vsbasicvsr/BasicVSR_REDS4.pth
vsbasicvsr/BasicVSR_Vimeo90K_BDx4.pth
vsbasicvsr/BasicVSR_Vimeo90K_BIx4.pth
vsbasicvsr/__init__.py
vsbasicvsr/arch_util.py
vsbasicvsr/basicvsr_arch.py
vsbasicvsr/registry.py
vsbasicvsr/spynet_arch.py
vsbasicvsr-1.2.0.dist-info/LICENSE
vsbasicvsr-1.2.0.dist-info/METADATA
vsbasicvsr-1.2.0.dist-info/WHEEL
vsbasicvsr-1.2.0.dist-info/top_level.txt
vsbasicvsr-1.2.0.dist-info/RECORD
