Metadata-Version: 2.1
Name: vsbasicvsr
Version: 1.2.0
Summary: BasicVSR function for VapourSynth
Home-page: https://github.com/HolyWu/vs-basicvsr
Author: HolyWu
License: UNKNOWN
Platform: UNKNOWN
Classifier: License :: OSI Approved :: Apache Software License
Classifier: Operating System :: OS Independent
Classifier: Programming Language :: Python :: 3
Classifier: Programming Language :: Python :: 3 :: Only
Classifier: Topic :: Multimedia :: Video
Requires-Python: >=3.6
License-File: LICENSE
Requires-Dist: numpy
Requires-Dist: torch
